examples/BCW2011Hedging.py
examples/BCW2011Liquidation.py
examples/test.py
hjb_solver/__init__.py
hjb_solver/config.py
hjb_solver/imports.py
hjb_solver/utils.py
hjb_solver/core/__init__.py
hjb_solver/core/abstraction.py
hjb_solver/core/main.py
hjb_solver/core/mixin.py
hjb_solver/core/structure.py
hjb_solver-0.1.0.dist-info/METADATA
hjb_solver-0.1.0.dist-info/WHEEL
hjb_solver-0.1.0.dist-info/top_level.txt
hjb_solver-0.1.0.dist-info/RECORD
