Metadata-Version: 2.4
Name: hjb-solver
Version: 0.1.0
Summary: Add your description here
Author-email: Haotian Deng <haotiandeng@stu.sufe.edu.cn>
Requires-Python: >=3.12
Requires-Dist: flax>=0.11.2
Requires-Dist: ipykernel>=6.30.1
Requires-Dist: ipywidgets>=8.1.7
Requires-Dist: jax>=0.7.1
Requires-Dist: jaxtyping>=0.3.2
Requires-Dist: loguru>=0.7.3
Requires-Dist: matplotlib>=3.10.6
Requires-Dist: numpy>=2.3.2
Requires-Dist: openpyxl>=3.1.5
Requires-Dist: pandas>=2.3.2
Requires-Dist: panel-print>=0.1.0
Requires-Dist: pathlib>=1.0.1
Requires-Dist: pretty-errors>=1.2.25
Requires-Dist: pyarrow>=21.0.0
Requires-Dist: rich>=14.1.0
Requires-Dist: tqdm>=4.67.1
